LICENSE
MANIFEST.in
README.rst
setup.cfg
setup.py
examples/simple.py
nasa_tle_loader/__init__.py
nasa_tle_loader/client.py
nasa_tle_loader/constants.py
nasa_tle_loader/log.py
nasa_tle_loader/parser.py
nasa_tle_loader/serialize.py
nasa_tle_loader/utils.py
nasa_tle_loader.egg-info/PKG-INFO
nasa_tle_loader.egg-info/SOURCES.txt
nasa_tle_loader.egg-info/dependency_links.txt
nasa_tle_loader.egg-info/requires.txt
nasa_tle_loader.egg-info/top_level.txt