Metadata-Version: 1.1
Name: nasa-tle-loader
Version: 1.0.0
Summary: Small TLE loader from NASA
Home-page: https://github.com/nkoshell/nasa-tle-loader
Author: nkoshell
Author-email: nikita.koshelev@gmail.com
License: MIT
Download-URL: https://github.com/nkoshell/nasa-tle-loader/archive/1.0.0.tar.gz
Platform: UNKNOWN
